chucky/__init__.py
chucky/client.py
chucky/tools.py
chucky/types.py
chucky/utils.py
chucky_sdk-0.2.0.dist-info/METADATA
chucky_sdk-0.2.0.dist-info/WHEEL
chucky_sdk-0.2.0.dist-info/RECORD
