Metadata-Version: 2.4
Name: chucky-sdk
Version: 0.2.0
Summary: Python SDK for Chucky - Claude Agent as a Service
License-Expression: MIT
Keywords: agent,ai,anthropic,claude,sdk
Classifier: Development Status :: 3 - Alpha
Classifier: Intended Audience :: Developers
Classifier: License :: OSI Approved :: MIT License
Classifier: Programming Language :: Python :: 3
Classifier: Programming Language :: Python :: 3.10
Classifier: Programming Language :: Python :: 3.11
Classifier: Programming Language :: Python :: 3.12
Classifier: Topic :: Scientific/Engineering :: Artificial Intelligence
Requires-Python: >=3.10
Requires-Dist: pydantic>=2.0
Requires-Dist: websockets>=12.0
Provides-Extra: dev
Requires-Dist: pytest-asyncio>=0.21; extra == 'dev'
Requires-Dist: pytest>=7.0; extra == 'dev'
Requires-Dist: python-dotenv>=1.0; extra == 'dev'
